win_pip/winpip.py
winpip-1.0.dist-info/LICENSE.txt
winpip-1.0.dist-info/METADATA
winpip-1.0.dist-info/WHEEL
winpip-1.0.dist-info/top_level.txt
winpip-1.0.dist-info/RECORD
