Metadata-Version: 2.1
Name: winpip
Version: 1.0
Summary: This Lets the windows interpreter programmer to manage pip commands in python programme
Home-page: https://github.com/GaneshKaricharla2000/win-pip
Author: Karicharla GNV Swamy Naidu
Author-email: ganeshkaricherla@gmail.com
License: MIT
Platform: UNKNOWN
Classifier: License :: OSI Approved :: MIT License
Classifier: Programming Language :: Python
